lkbodysegmentation/__init__.py
lkbodysegmentation-0.0.1.dist-info/METADATA
lkbodysegmentation-0.0.1.dist-info/WHEEL
lkbodysegmentation-0.0.1.dist-info/top_level.txt
lkbodysegmentation-0.0.1.dist-info/RECORD
