Metadata-Version: 2.1
Name: lkbodysegmentation
Version: 0.0.1
Summary: Subtract the background from orignal Image.
Home-page: https://www.lakshaykumar.tech/
Author: Lakshay Kumar
Author-email: contact@lakshaykumar.tech
License: MIT
Platform: UNKNOWN
Classifier: Programming Language :: Python :: 3
Classifier: License :: OSI Approved :: MIT License
Classifier: Operating System :: OS Independent
Requires-Python: >=3.3
Requires-Dist: mediapipe
Requires-Dist: cvzone
